basalt_protocol/__init__.py
basalt_protocol/basalt_pb2.py
basalt_protocol/basalt_pb2_grpc.py
basalt_protocol-0.1.1.dist-info/METADATA
basalt_protocol-0.1.1.dist-info/WHEEL
basalt_protocol-0.1.1.dist-info/top_level.txt
basalt_protocol-0.1.1.dist-info/RECORD
