Metadata-Version: 2.4
Name: basalt-protocol
Version: 0.1.1
Summary: Basalt gRPC protocol definitions
Home-page: https://github.com/psila-ai/basalt-protocol
License: MIT
Requires-Python: >=3.8
Requires-Dist: grpcio>=1.60.0
Requires-Dist: grpcio-tools>=1.60.0
Requires-Dist: protobuf>=4.25.0
Dynamic: home-page
Dynamic: license
Dynamic: requires-dist
Dynamic: requires-python
Dynamic: summary
